lemonaid/__init__.py
lemonaid/client/__init__.py
lemonaid/client/_citra_client.py
lemonaid/client/_citra_elset_client.py
lemonaid/client/_ground_station_client.py
lemonaid/client/_requests.py
lemonaid/enums/__init__.py
lemonaid/enums/_citra_elset_type.py
lemonaid/enums/_citra_environment.py
lemonaid/schemas/__init__.py
lemonaid/schemas/_citra_base_model.py
lemonaid/schemas/_elset.py
lemonaid/schemas/_ground_station.py
lemonaid/schemas/_satellite_alias.py
lemonaid/schemas/normalization.py
lemonaid/settings/__init__.py
lemonaid/settings/_citra_client_settings.py
lemonaid-0.2.0.dist-info/METADATA
lemonaid-0.2.0.dist-info/WHEEL
lemonaid-0.2.0.dist-info/RECORD
